oceanograpy/__init__.py
oceanograpy/adcp_plot_tools.py
oceanograpy/example.py
oceanograpy/frma.py
oceanograpy/matplotlib_dhi.py
oceanograpy/processing_tools.py
oceanograpy/seabird_ctd.py
oceanograpy/workhorse_adcp.py
oceanograpy-0.0.7.dist-info/LICENSE
oceanograpy-0.0.7.dist-info/METADATA
oceanograpy-0.0.7.dist-info/WHEEL
oceanograpy-0.0.7.dist-info/top_level.txt
oceanograpy-0.0.7.dist-info/RECORD
