Metadata-Version: 2.1
Name: oceanograpy
Version: 0.0.7
Summary: Toolbox for importing and plotting ADCP and CTD data
Home-page: 
Author: Andy Banks
Author-email: 
Classifier: Programming Language :: Python :: 3
Classifier: License :: OSI Approved :: MIT License
Classifier: Operating System :: OS Independent
License-File: LICENSE
